qufi/__init__.py
qufi/config.py
qufi/version.py
qufi_script-1.0.2.dist-info/LICENSE
qufi_script-1.0.2.dist-info/METADATA
qufi_script-1.0.2.dist-info/WHEEL
qufi_script-1.0.2.dist-info/top_level.txt
qufi_script-1.0.2.dist-info/RECORD
