Metadata-Version: 2.1
Name: qufi-script
Version: 1.0.2
Summary: A python package that converts Oromo language script's witten in latin letters to geez letters
Home-page: https://github.com/natanimn/Qufi
Author: Natanim Negash
Author-email: natanimn@yahoo.com
License: GPLv3
Keywords: fidel,python,alphabet,amharic,oromo,letters,letters convertors,geez letters,geez,qube
License-File: LICENSE
